coastal_resilience_utilities/__init__.py
coastal_resilience_utilities/dataconf.py
coastal_resilience_utilities/test.py
coastal_resilience_utilities/damage_assessment/__init__.py
coastal_resilience_utilities/damage_assessment/damage_assessment.py
coastal_resilience_utilities/damage_assessment/nsi_assessment.py
coastal_resilience_utilities/damage_assessment/population_assessment.py
coastal_resilience_utilities/damage_assessment/scripts/NSI_processing/aggregate_vulnerability_curves.py
coastal_resilience_utilities/damage_assessment/scripts/NSI_processing/census_tract_processing.py
coastal_resilience_utilities/damage_assessment/supporting_data/__init__.py
coastal_resilience_utilities/damage_assessment/supporting_data/NSI_processing/aggregate_vulnerability_curves.py
coastal_resilience_utilities/damage_assessment/supporting_data/damage_curves_and_values/DDF_Global.csv
coastal_resilience_utilities/damage_assessment/supporting_data/damage_curves_and_values/MaxDamage_per_m2.csv
coastal_resilience_utilities/damage_assessment/supporting_data/damage_curves_and_values/__init__.py
coastal_resilience_utilities/damage_assessment/supporting_data/damage_curves_and_values/crosswalk_econ_gadm.csv
coastal_resilience_utilities/damage_assessment/supporting_data/damage_curves_and_values/nsi_median_vulnerability_curves.csv
coastal_resilience_utilities/damage_assessment/test/__init__.py
coastal_resilience_utilities/damage_assessment/test/test_damage_assessment.py
coastal_resilience_utilities/damage_assessment/tools/run_damage_assessment.py
coastal_resilience_utilities/damage_assessment_nsi_blocks/__init__.py
coastal_resilience_utilities/damage_assessment_nsi_blocks/pixel_assessment.py
coastal_resilience_utilities/damage_assessment_nsi_blocks/prep_blocks.py
coastal_resilience_utilities/damage_assessment_nsi_blocks/run_assessment.py
coastal_resilience_utilities/damage_assessment_nsi_blocks/test/__init__.py
coastal_resilience_utilities/damage_assessment_nsi_blocks/test/test_prep_blocks.py
coastal_resilience_utilities-0.1.37.dist-info/METADATA
coastal_resilience_utilities-0.1.37.dist-info/WHEEL
coastal_resilience_utilities-0.1.37.dist-info/top_level.txt
coastal_resilience_utilities-0.1.37.dist-info/RECORD
