Metadata-Version: 2.2
Name: coastal-resilience-utilities
Version: 0.1.37
Summary: A utility package for coastal resilience analysis.
Author-email: Chris Lowrie <lowriechris779@gmail.com>
License: MIT
Classifier: Programming Language :: Python :: 3
Classifier: License :: OSI Approved :: MIT License
Classifier: Operating System :: OS Independent
Requires-Python: <3.13,>=3.11
Requires-Dist: geospatial-analysis-environment==0.1.9
Requires-Dist: python-dotenv
Requires-Dist: gdal>=3.10.0
Requires-Dist: psycopg2-binary
